zipfile_zstd/__init__.py
zipfile_zstd/_patcher.py
zipfile_zstd/_zipfile.py
zipfile_zstd-0.0.4.dist-info/LICENSE
zipfile_zstd-0.0.4.dist-info/METADATA
zipfile_zstd-0.0.4.dist-info/WHEEL
zipfile_zstd-0.0.4.dist-info/top_level.txt
zipfile_zstd-0.0.4.dist-info/RECORD
