Metadata-Version: 2.1
Name: zipfile-zstd
Version: 0.0.4
Summary: Monkey patch the standard zipfile module to enable Zstandard support
Home-page: https://github.com/taisei-project/python-zipfile-zstd
Author: Andrei Alexeyev
Author-email: akari@taisei-project.org
License: UNKNOWN
Project-URL: Bug Tracker, https://github.com/taisei-project/python-zipfile-zstd/issues
Keywords: zip zipfile zstd zstandard
Platform: UNKNOWN
Classifier: Intended Audience :: Developers
Classifier: Programming Language :: Python :: 3
Classifier: License :: OSI Approved :: MIT License
Classifier: Operating System :: OS Independent
Classifier: Topic :: System :: Archiving
Classifier: Topic :: System :: Archiving :: Compression
Requires-Python: >=3.6
License-File: LICENSE
